[
  {
    "id": 1,
    "heading": "Efficient Collaborating",
    "text": "Lorem ipsum dolor sit amet, consectetur adipiscing elit. Auctor neque sed imperdiet nibh lectus feugiat nunc sem.",
    "avatar": {
      "src": "https://images.unsplash.com/photo-1586297135537-94bc9ba060aa?ixid=MXwxMjA3fDB8MHxwaG90by1wYWdlfHx8fGVufDB8fHw%3D&ixlib=rb-1.2.1&auto=format&fit=crop&w=100&q=80",
      "name": "Jane Doe",
      "title": "CEO at XYZ Co."
    }
  },
  {
    "id": 2,
    "heading": "Great Support",
    "text": "Lorem ipsum dolor sit amet, consectetur adipiscing elit. Auctor neque sed imperdiet nibh lectus feugiat nunc sem.",
    "avatar": {
      "src": "https://images.unsplash.com/photo-1586297135537-94bc9ba060aa?ixid=MXwxMjA3fDB8MHxwaG90by1wYWdlfHx8fGVufDB8fHw%3D&ixlib=rb-1.2.1&auto=format&fit=crop&w=100&q=80",
      "name": "John Doe",
      "title": "CTO at XYZ Co."
    }
  },
  {
    "id": 3,
    "heading": "Efficient Asslicking",
    "text": "Lorem ipsum dolor sit amet, consectetur adipiscing elit. Auctor neque sed imperdiet nibh lectus feugiat nunc sem.",
    "avatar": {
      "src": "https://images.unsplash.com/photo-1586297135537-94bc9ba060aa?ixid=MXwxMjA3fDB8MHxwaG90by1wYWdlfHx8fGVufDB8fHw%3D&ixlib=rb-1.2.1&auto=format&fit=crop&w=100&q=80",
      "name": "Jane Doe",
      "title": "CEO at XYZ Co."
    }
  },
  {
    "id": 4,
    "heading": "Show Tits",
    "text": "Lorem ipsum dolor sit amet, consectetur adipiscing elit. Auctor neque sed imperdiet nibh lectus feugiat nunc sem.",
    "avatar": {
      "src": "https://images.unsplash.com/photo-1586297135537-94bc9ba060aa?ixid=MXwxMjA3fDB8MHxwaG90by1wYWdlfHx8fGVufDB8fHw%3D&ixlib=rb-1.2.1&auto=format&fit=crop&w=100&q=80",
      "name": "John Doe",
      "title": "CTO at XYZ Co."
    }
  }
]
